cookiecutter.json
hooks/post_gen_project.py
hooks/pre_gen_project.py
pyckage_cookiecutter/__init__.py
pyckage_cookiecutter/main.py
{{cookiecutter.__project_slug}}/.github/workflows/release.yml
{{cookiecutter.__project_slug}}/.github/workflows/sphinx.yml
{{cookiecutter.__project_slug}}/.github/workflows/test.yml
{{cookiecutter.__project_slug}}/.gitignore
{{cookiecutter.__project_slug}}/.gitlab-ci.yml
{{cookiecutter.__project_slug}}/CONTRIBUTING.rst
{{cookiecutter.__project_slug}}/LICENSES/2-Clause BSD
{{cookiecutter.__project_slug}}/LICENSES/3-Clause BSD
{{cookiecutter.__project_slug}}/LICENSES/APACHE
{{cookiecutter.__project_slug}}/LICENSES/GPL
{{cookiecutter.__project_slug}}/LICENSES/MIT
{{cookiecutter.__project_slug}}/MANIFEST.in
{{cookiecutter.__project_slug}}/Makefile
{{cookiecutter.__project_slug}}/README.rst
{{cookiecutter.__project_slug}}/bitbucket-pipelines.yml
{{cookiecutter.__project_slug}}/docs/Makefile
{{cookiecutter.__project_slug}}/docs/make.bat
{{cookiecutter.__project_slug}}/docs/source/01_about.rst
{{cookiecutter.__project_slug}}/docs/source/02_source.rst
{{cookiecutter.__project_slug}}/docs/source/03_authors.rst
{{cookiecutter.__project_slug}}/docs/source/04_contributing.rst
{{cookiecutter.__project_slug}}/docs/source/conf.py
{{cookiecutter.__project_slug}}/docs/source/index.rst
{{cookiecutter.__project_slug}}/pyproject.toml
{{cookiecutter.__project_slug}}/setup.cfg
{{cookiecutter.__project_slug}}/tests/__init__.py
{{cookiecutter.__project_slug}}/tests/conftest.py
{{cookiecutter.__project_slug}}/tests/resources/.keep
{{cookiecutter.__project_slug}}/tests/test_version.py
{{cookiecutter.__project_slug}}/{{cookiecutter.__project_slug}}/__init__.py
pyckage_cookiecutter-1.0.2.dist-info/LICENSE
pyckage_cookiecutter-1.0.2.dist-info/METADATA
pyckage_cookiecutter-1.0.2.dist-info/WHEEL
pyckage_cookiecutter-1.0.2.dist-info/entry_points.txt
pyckage_cookiecutter-1.0.2.dist-info/RECORD
