Metadata-Version: 2.1
Name: Pyckage-Cookiecutter
Version: 1.0.2
Summary: This projects consist of a cookiecutter template that generates a full structure for a creating a PyPi standard package.
Home-page: https://github.com/zhiwei2017/pyckage-cookiecutter
License: MIT
Keywords: cookiecutter template,python38,python39,python310,github-actions,gitlab-ci,bitbucket-pipelines
Author: Zhiwei Zhang
Author-email: zhiwei2017@gmail.com
Requires-Python: >=3.8.1,<4.0.0
Classifier: Development Status :: 5 - Production/Stable
Classifier: Intended Audience :: Developers
Classifier: License :: OSI Approved :: MIT License
Classifier: Natural Language :: English
Classifier: Operating System :: OS Independent
Classifier: Programming Language :: Python
Classifier: Programming Language :: Python :: 3
Classifier: Programming Language :: Python :: 3.9
Classifier: Programming Language :: Python :: 3.10
Classifier: Programming Language :: Python :: 3.11
Classifier: Programming Language :: Python :: 3.12
Classifier: Programming Language :: Python :: 3.8
Classifier: Programming Language :: Python :: Implementation
Classifier: Topic :: Utilities
Requires-Dist: cookiecutter (>=2.4,<2.5)
Project-URL: Documentation, https://zhiwei2017.github.io/pyckage-cookiecutter/
Project-URL: Repository, https://github.com/zhiwei2017/pyckage-cookiecutter
